{
	"storyName": "Your New Week",
	"difficulties": "hard",
	"hideFreeplay": false,
	"weekBackground": "stage",
	"freeplayColor": [
		146,
		113,
		253
	],
	"weekBefore": "tutorial",
	"startUnlocked": true,
	"weekCharacters": [
		"dad",
		"bf",
		"gf"
	],
	"songs": [
		[
			"satisflatter",
			"sakuroma",
			[
				255,
				113,
				253
			]
		],
		[
			"satisfracture-remix",
			"retro-minus",
			[
				146,
				113,
				253
			]
		],
		[
			"ectogasm",
			"zerktro",
			[
				146,
				113,
				253
			]
		],
		[
			"scalie-feeling",
			"sakuroma",
			[
				255,
				113,
				253
			]
		],
		[
			"fuzziest-feeling",
			"sakuroma",
			[
				255,
				113,
				253
			]
		]
	],
	"hideStoryMode": true,
	"weekName": "Custom Week",
	"hiddenUntilUnlocked": false
}